dogma/__init__.py
dogma/angle.py
dogma/latitude.py
dogma/longitude.py
dogma.py-0.0.1.dist-info/METADATA
dogma.py-0.0.1.dist-info/UNLICENSE
dogma.py-0.0.1.dist-info/WHEEL
dogma.py-0.0.1.dist-info/top_level.txt
dogma.py-0.0.1.dist-info/RECORD
