Metadata-Version: 2.1
Name: dogma.py
Version: 0.0.1
Summary: Dogma for Python
Home-page: https://github.com/dogmatists/dogma.py
Author: Arto Bendiken
Author-email: arto@bendiken.net
License: Public Domain
Project-URL: Source, https://github.com/dogmatists/dogma.py
Platform: UNKNOWN
Classifier: Development Status :: 2 - Pre-Alpha
Classifier: Environment :: Console
Classifier: Intended Audience :: Developers
Classifier: Intended Audience :: Information Technology
Classifier: License :: Public Domain
Classifier: Natural Language :: English
Classifier: Operating System :: OS Independent
Classifier: Programming Language :: Python :: 3 :: Only
Classifier: Programming Language :: Python :: 3.6
Classifier: Programming Language :: Python :: 3.7
Classifier: Programming Language :: Python :: 3.8
Classifier: Programming Language :: Python :: 3.9
Classifier: Topic :: Software Development :: Libraries
Requires-Python: ~=3.6
Provides-Extra: test
Requires-Dist: pytest ; extra == 'test'
